__init__.py
customdataclass.py
customdataclass-0.1.2.dist-info/LICENSE.md
customdataclass-0.1.2.dist-info/METADATA
customdataclass-0.1.2.dist-info/WHEEL
customdataclass-0.1.2.dist-info/top_level.txt
customdataclass-0.1.2.dist-info/RECORD
