Metadata-Version: 2.1
Name: customdataclass
Version: 0.1.2
Summary: A custom dataclass implementation
Author-email: Lorenzo Rossi <pypi@lorenzoros.si>
License: MIT
Project-URL: Homepage, https://github.com/lorossi/customdataclass
Project-URL: Bug Tracker, https://github.com/lorossi/customdataclass/issues
Project-URL: documentation, https://lorossi.github.io/customdataclass/
Classifier: Programming Language :: Python :: 3
Classifier: Operating System :: OS Independent
Requires-Python: >=3.7
License-File: LICENSE.md
Requires-Dist: PyYAML >=6.0.1
Requires-Dist: toml >=0.10.2
Requires-Dist: ujson >=5.8.0
